<?xml version="1.0" encoding="UTF-8"?>
<objects serializationModel="Studio.02.02.00">
	<object class="AudioFile" id="{de340674-18d2-4aba-b02e-eeb29849276f}">
		<property name="assetPath">
			<value>Character/Jump/Dirt/Footsteps, Human, Jump, Land, Ground, Gravel SND62070 - Trimmed (3).wav</value>
		</property>
		<property name="frequencyInKHz">
			<value>96</value>
		</property>
		<property name="channelCount">
			<value>1</value>
		</property>
		<property name="length">
			<value>0.53119791666666671</value>
		</property>
		<relationship name="masterAssetFolder">
			<destination>{e1a0a078-1c7f-4506-a300-d85db398eb86}</destination>
		</relationship>
	</object>
</objects>
